id_manual_tools/__init__.py
id_manual_tools/concatenate_traj.py
id_manual_tools/correct_trajectories.py
id_manual_tools/get_nans.py
id_manual_tools/matplotlib_gui.py
id_manual_tools/plot_trajectories.py
id_manual_tools/set_corners.py
id_manual_tools/utils.py
id_manual_tools-1.0.1.dist-info/licenses/LICENCE
id_manual_tools-1.0.1.dist-info/METADATA
id_manual_tools-1.0.1.dist-info/WHEEL
id_manual_tools-1.0.1.dist-info/entry_points.txt
id_manual_tools-1.0.1.dist-info/top_level.txt
id_manual_tools-1.0.1.dist-info/RECORD
