Metadata-Version: 2.4
Name: id_manual_tools
Version: 1.0.1
Summary: Tools for using idtracker.ai
Author-email: Jordi Torrents <jordi.torrentsm@gmail.com>
Project-URL: Repository, https://github.com/jordi-torrents/id_manual_tools
Classifier: Programming Language :: Python :: 3
Classifier: License :: OSI Approved :: MIT License
Classifier: Operating System :: OS Independent
Requires-Python: >=3.7
License-File: LICENCE
Requires-Dist: matplotlib
Requires-Dist: numpy
Requires-Dist: opencv-python
Requires-Dist: rich
Requires-Dist: scipy
Dynamic: license-file
